fastapi_cognito/__init__.py
fastapi_cognito/cognito_jwt/__init__.py
fastapi_cognito/cognito_jwt/constants.py
fastapi_cognito/cognito_jwt/decode.py
fastapi_cognito/cognito_jwt/exceptions.py
fastapi_cognito/cognito_jwt/utils.py
fastapi_cognito/exceptions.py
fastapi_cognito/fastapi_cognito.py
fastapi_cognito/models.py
fastapi_cognito/settings_parsers.py
fastapi_cognito-2.9.0.dist-info/LICENSE.txt
fastapi_cognito-2.9.0.dist-info/METADATA
fastapi_cognito-2.9.0.dist-info/WHEEL
fastapi_cognito-2.9.0.dist-info/RECORD
