Metadata-Version: 2.3
Name: fastapi-cognito
Version: 2.9.0
Summary: AWS Cognito JWT authentication library for FastAPI
License: MIT
Author: Marko Mirosavljev
Author-email: mirosavljevm023@gmail.com
Maintainer: Marko Mirosavljev
Maintainer-email: mirosavljevm023@gmail.com
Requires-Python: >=3.8,<4.0
Classifier: Framework :: FastAPI
Classifier: Intended Audience :: Developers
Classifier: License :: OSI Approved :: MIT License
Classifier: Operating System :: OS Independent
Classifier: Programming Language :: Python :: 3
Classifier: Programming Language :: Python :: 3.8
Classifier: Programming Language :: Python :: 3.9
Classifier: Programming Language :: Python :: 3.10
Classifier: Programming Language :: Python :: 3.11
Classifier: Programming Language :: Python :: 3.12
Classifier: Programming Language :: Python :: 3.13
Requires-Dist: aiofile (>=3.8.8)
Requires-Dist: async-lru (>=2.0.4)
Requires-Dist: fastapi (>=0.111.0,<1.0.0)
Requires-Dist: httpx (>=0.27.0)
Requires-Dist: joserfc (>=0.9.0)
Requires-Dist: pydantic (>=2.7.1)
Requires-Dist: pydantic-settings (>=2.2.1)
Requires-Dist: pyyaml (>=6.0.1)
Project-URL: Repository, https://github.com/markomirosavljev/fastapi-cognito
